gseqnmf/__init__.py
gseqnmf/exceptions.py
gseqnmf/gseqnmf.py
gseqnmf/plotting.py
gseqnmf/support.py
gseqnmf/validation.py
gseqnmf-0.0.3.dist-info/licenses/LICENSE
gseqnmf-0.0.3.dist-info/METADATA
gseqnmf-0.0.3.dist-info/WHEEL
gseqnmf-0.0.3.dist-info/top_level.txt
gseqnmf-0.0.3.dist-info/RECORD
