Metadata-Version: 2.4
Name: gseqnmf
Version: 0.0.3
Summary: seqNMF with GPU support & sklearn syntax
Author: Darik A. O'Neil
Maintainer: Darik A. O'Neil
License: MIT License
Project-URL: documentation, https://github.com/darikoneil/gseqNMF
Project-URL: repository, https://github.com/darikoneil/gseqNMF
Keywords: KEYWORD
Classifier: Programming Language :: Python
Requires-Python: <=4.0,>=3.12
License-File: LICENSE
Requires-Dist: numba>=0.62.1
Requires-Dist: numpy>=2.3.3
Requires-Dist: scikit-learn>=1.7.2
Requires-Dist: setuptools>=80.9.0
Requires-Dist: tqdm>=4.67.1
Provides-Extra: cuda12
Requires-Dist: cupy-cuda12x; extra == "cuda12"
Provides-Extra: test
Requires-Dist: importlib-metadata; extra == "test"
Requires-Dist: polars[numpy,pyarrow]; extra == "test"
Requires-Dist: pytest; extra == "test"
Requires-Dist: pytest-sugar; extra == "test"
Requires-Dist: pytest-clarity; extra == "test"
Requires-Dist: pytest-mock; extra == "test"
Requires-Dist: toml; extra == "test"
Requires-Dist: tomli-w; extra == "test"
Provides-Extra: lint
Requires-Dist: flake8; extra == "lint"
Requires-Dist: flake8-annotations-complexity; extra == "lint"
Requires-Dist: flake8-class-attributes-order; extra == "lint"
Requires-Dist: flake8-dunder-all; extra == "lint"
Requires-Dist: flake8-html; extra == "lint"
Requires-Dist: ruff; extra == "lint"
Provides-Extra: cov
Requires-Dist: coverage[toml]; extra == "cov"
Requires-Dist: coveralls; extra == "cov"
Requires-Dist: toml; extra == "cov"
Requires-Dist: tomli-w; extra == "cov"
Provides-Extra: docs
Requires-Dist: sphinx; extra == "docs"
Requires-Dist: sphinx-autodoc-typehints; extra == "docs"
Requires-Dist: autodoc_pydantic; extra == "docs"
Requires-Dist: sphinx-rtd-theme; extra == "docs"
Requires-Dist: jinja2; extra == "docs"
Provides-Extra: vis
Requires-Dist: cmocean; extra == "vis"
Requires-Dist: matplotlib; extra == "vis"
Requires-Dist: PyQt6; extra == "vis"
Provides-Extra: dev
Requires-Dist: gseqNMF[test]; extra == "dev"
Requires-Dist: gseqNMF[lint]; extra == "dev"
Requires-Dist: gseqNMF[cov]; extra == "dev"
Requires-Dist: gseqNMF[docs]; extra == "dev"
Requires-Dist: gseqNMF[prod]; extra == "dev"
Requires-Dist: gseqNMF[vis]; extra == "dev"
Dynamic: license-file
